[{"name":"Rot","color":"#ff0000","measures":{"5%":{"spectrum":{"sensor":"7262","max":135,"values":["0.043","0.044","0.056","0.084","0.701","0.993"]},"xyY":["0.5884","0.3651","0.0465"],"XYZ":["1.1299","0.701","0.0893"],"RGB":["255","173","84"],"color":"rgb(255, 173, 84)"},"10%":{"spectrum":{"sensor":"7262","max":360,"values":["0.029","0.029","0.036","0.069","0.717","0.999"]},"xyY":["0.6055","0.3621","0.0325"],"XYZ":["1.123","0.6716","0.0602"],"RGB":["255","165","69"],"color":"rgb(255, 165, 69)"},"20%":{"spectrum":{"sensor":"7262","max":1225,"values":["0.024","0.02","0.027","0.062","0.723","1"]},"xyY":["0.6128","0.3599","0.0273"],"XYZ":["1.1186","0.6569","0.0499"],"RGB":["255","161","63"],"color":"rgb(255, 161, 63)"},"35%":{"spectrum":{"sensor":"7262","max":3665,"values":["0.023","0.018","0.025","0.061","0.717","1"]},"xyY":["0.6147","0.3592","0.0261"],"XYZ":["1.1102","0.6487","0.0472"],"RGB":["255","160","62"],"color":"rgb(255, 160, 62)"},"50%":{"spectrum":{"sensor":"7262","max":7461,"values":["0.023","0.017","0.024","0.059","0.702","1"]},"xyY":["0.6156","0.3586","0.0257"],"XYZ":["1.0926","0.6365","0.0457"],"RGB":["255","158","61"],"color":"rgb(255, 158, 61)"},"65%":{"spectrum":{"sensor":"7262","max":12672,"values":["0.022","0.017","0.023","0.057","0.677","1"]},"xyY":["0.6166","0.358","0.0253"],"XYZ":["1.0636","0.6176","0.0437"],"RGB":["255","156","59"],"color":"rgb(255, 156, 59)"},"85%":{"spectrum":{"sensor":"7262","max":21992,"values":["0.02","0.016","0.021","0.055","0.636","1"]},"xyY":["0.6178","0.3569","0.0252"],"XYZ":["1.0165","0.5873","0.0415"],"RGB":["255","152","58"],"color":"rgb(255, 152, 58)"},"100%":{"spectrum":{"sensor":"7262","max":30851,"values":["0.019","0.016","0.02","0.052","0.592","1"]},"xyY":["0.6192","0.3557","0.0251"],"XYZ":["0.9669","0.5555","0.0392"],"RGB":["255","147","57"],"color":"rgb(255, 147, 57)"}}},{"name":"Grün","color":"#00ff00","measures":{"5%":{"spectrum":{"sensor":"7262","max":154,"values":["0.053","0.998","0.386","0.149","0.026","0.016"]},"xyY":["0.2133","0.5523","0.2344"],"XYZ":["0.3353","0.8678","0.3684"],"RGB":["0","255","160"],"color":"rgb(0, 255, 160)"},"10%":{"spectrum":{"sensor":"7262","max":437,"values":["0.034","0.998","0.376","0.14","0.016","0.01"]},"xyY":["0.206","0.5676","0.2265"],"XYZ":["0.3055","0.8418","0.3359"],"RGB":["0","255","154"],"color":"rgb(0, 255, 154)"},"20%":{"spectrum":{"sensor":"7262","max":1511,"values":["0.03","1","0.373","0.135","0.01","0.005"]},"xyY":["0.201","0.5727","0.2263"],"XYZ":["0.2917","0.831","0.3283"],"RGB":["0","255","152"],"color":"rgb(0, 255, 152)"},"35%":{"spectrum":{"sensor":"7262","max":4537,"values":["0.028","1","0.374","0.135","0.009","0.005"]},"xyY":["0.2006","0.5744","0.2251"],"XYZ":["0.2901","0.8308","0.3255"],"RGB":["0","255","151"],"color":"rgb(0, 255, 151)"},"50%":{"spectrum":{"sensor":"7262","max":9092,"values":["0.028","1","0.378","0.137","0.009","0.004"]},"xyY":["0.2013","0.5749","0.2238"],"XYZ":["0.2929","0.8363","0.3255"],"RGB":["0","255","151"],"color":"rgb(0, 255, 151)"},"65%":{"spectrum":{"sensor":"7262","max":15073,"values":["0.029","1","0.384","0.139","0.009","0.004"]},"xyY":["0.2026","0.5752","0.2222"],"XYZ":["0.2976","0.8446","0.3263"],"RGB":["0","255","152"],"color":"rgb(0, 255, 152)"},"85%":{"spectrum":{"sensor":"7262","max":25142,"values":["0.029","1","0.395","0.144","0.009","0.004"]},"xyY":["0.2052","0.5756","0.2192"],"XYZ":["0.3069","0.8611","0.3279"],"RGB":["0","255","152"],"color":"rgb(0, 255, 152)"},"100%":{"spectrum":{"sensor":"7262","max":33678,"values":["0.031","1","0.409","0.151","0.009","0.004"]},"xyY":["0.2082","0.576","0.2158"],"XYZ":["0.3183","0.8808","0.3299"],"RGB":["0","255","152"],"color":"rgb(0, 255, 152)"}}},{"name":"Blau","color":"#0000ff","measures":{"5%":{"spectrum":{"sensor":"7262","max":320,"values":["0.999","0.211","0.027","0.018","0.013","0.01"]},"xyY":["0.16","0.0671","0.7729"],"XYZ":["0.3784","0.1587","1.8286"],"RGB":["0","121","255"],"color":"rgb(0, 121, 255)"},"10%":{"spectrum":{"sensor":"7262","max":922,"values":["0.999","0.205","0.018","0.011","0.007","0.005"]},"xyY":["0.1554","0.059","0.7856"],"XYZ":["0.3614","0.1372","1.8268"],"RGB":["0","114","255"],"color":"rgb(0, 114, 255)"},"20%":{"spectrum":{"sensor":"7262","max":3208,"values":["1","0.203","0.013","0.009","0.004","0.003"]},"xyY":["0.1537","0.0557","0.7906"],"XYZ":["0.3553","0.1287","1.8271"],"RGB":["0","112","255"],"color":"rgb(0, 112, 255)"},"35%":{"spectrum":{"sensor":"7262","max":9666,"values":["1","0.204","0.012","0.008","0.004","0.003"]},"xyY":["0.1532","0.0549","0.7919"],"XYZ":["0.3536","0.1268","1.8276"],"RGB":["0","111","255"],"color":"rgb(0, 111, 255)"},"50%":{"spectrum":{"sensor":"7262","max":19432,"values":["1","0.206","0.012","0.008","0.004","0.003"]},"xyY":["0.153","0.055","0.7919"],"XYZ":["0.3533","0.127","1.8282"],"RGB":["0","111","255"],"color":"rgb(0, 111, 255)"},"65%":{"spectrum":{"sensor":"7262","max":32417,"values":["1","0.21","0.012","0.008","0.004","0.003"]},"xyY":["0.1529","0.0554","0.7917"],"XYZ":["0.3532","0.128","1.8292"],"RGB":["0","112","255"],"color":"rgb(0, 112, 255)"},"85%":{"spectrum":{"sensor":"7262","max":54647,"values":["1","0.216","0.012","0.008","0.004","0.003"]},"xyY":["0.1526","0.0563","0.7911"],"XYZ":["0.3532","0.1302","1.831"],"RGB":["0","113","255"],"color":"rgb(0, 113, 255)"},"100%":{"spectrum":{"sensor":"7262","max":74243,"values":["1","0.224","0.012","0.008","0.003","0.003"]},"xyY":["0.1523","0.0573","0.7904"],"XYZ":["0.3533","0.1328","1.8331"],"RGB":["0","114","255"],"color":"rgb(0, 114, 255)"}}},{"name":"Weiss","color":"#ffffff","measures":{"5%":{"spectrum":{"sensor":"7262","max":115,"values":["0.994","0.432","0.761","0.697","0.251","0.174"]},"xyY":["0.2924","0.3429","0.3647"],"XYZ":["1.5131","1.7747","1.8871"],"RGB":["255","255","255"],"color":"rgb(255, 255, 255)"},"10%":{"spectrum":{"sensor":"7262","max":326,"values":["0.999","0.417","0.756","0.696","0.245","0.163"]},"xyY":["0.2915","0.3414","0.3671"],"XYZ":["1.5022","1.7593","1.8916"],"RGB":["255","255","255"],"color":"rgb(255, 255, 255)"},"20%":{"spectrum":{"sensor":"7262","max":1143,"values":["1","0.412","0.753","0.695","0.239","0.162"]},"xyY":["0.2908","0.3407","0.3685"],"XYZ":["1.4934","1.7492","1.8921"],"RGB":["255","255","255"],"color":"rgb(255, 255, 255)"},"35%":{"spectrum":{"sensor":"7262","max":3424,"values":["1","0.41","0.748","0.691","0.238","0.16"]},"xyY":["0.2905","0.34","0.3695"],"XYZ":["1.4871","1.7402","1.8912"],"RGB":["255","255","255"],"color":"rgb(255, 255, 255)"},"50%":{"spectrum":{"sensor":"7262","max":6901,"values":["1","0.41","0.747","0.69","0.236","0.16"]},"xyY":["0.2902","0.3397","0.3701"],"XYZ":["1.4832","1.7359","1.8916"],"RGB":["255","255","255"],"color":"rgb(255, 255, 255)"},"65%":{"spectrum":{"sensor":"7262","max":11489,"values":["1","0.411","0.745","0.689","0.236","0.16"]},"xyY":["0.2901","0.3395","0.3704"],"XYZ":["1.4821","1.734","1.8919"],"RGB":["255","255","255"],"color":"rgb(255, 255, 255)"},"85%":{"spectrum":{"sensor":"7262","max":19418,"values":["1","0.413","0.743","0.687","0.235","0.161"]},"xyY":["0.2899","0.3392","0.3709"],"XYZ":["1.4792","1.7304","1.8925"],"RGB":["255","255","255"],"color":"rgb(255, 255, 255)"},"100%":{"spectrum":{"sensor":"7262","max":26385,"values":["1","0.415","0.74","0.685","0.235","0.161"]},"xyY":["0.2897","0.3388","0.3715"],"XYZ":["1.4761","1.7261","1.8931"],"RGB":["255","255","255"],"color":"rgb(255, 255, 255)"}}},{"name":"Rot","color":"#ff0000","measures":{}},{"name":"Grün","color":"#00ff00","measures":{}},{"name":"Blau","color":"#0000ff","measures":{}},{"name":"Weiss","color":"#ffffff","measures":{}}]